wsqluse/__init__.py
wsqluse/functions.py
wsqluse/settings.py
wsqluse/wsqluse.py
wsqluse/tests/__init__.py
wsqluse/tests/general_test_funcs.py
wsqluse/tests/get_dict_test.py
wsqluse/tests/main_test.py
wsqluse/tests/test_cfg.py
wsqluse/tests/try_execute_funcs_test.py
wsqluse/tests/try_execute_get_test.py
wsqluse-2.2.dist-info/METADATA
wsqluse-2.2.dist-info/WHEEL
wsqluse-2.2.dist-info/top_level.txt
wsqluse-2.2.dist-info/RECORD
