Metadata-Version: 2.4
Name: wsqluse
Version: 2.2
Author: PunchyArchy
Author-email: ksmdrmvscthny@gmail.com
Requires-Dist: psycopg2-binary
Dynamic: author
Dynamic: author-email
Dynamic: requires-dist
